enhanced_downloader/__init__.py
enhanced_downloader/downloader.py
enhanced_downloader-0.2.3.dist-info/licenses/LICENSE
enhanced_downloader-0.2.3.dist-info/METADATA
enhanced_downloader-0.2.3.dist-info/WHEEL
enhanced_downloader-0.2.3.dist-info/top_level.txt
enhanced_downloader-0.2.3.dist-info/RECORD
