Metadata-Version: 2.4
Name: enhanced_downloader
Version: 0.2.3
Summary: 一个功能强大的增强型下载模块，支持多线程下载、断点续传和进度显示
Home-page: https://github.com/Stabvalue/enhanced_downloader
Author: Stabvalue
Author-email: stabvalue@outlook.com
License: MIT
Project-URL: Bug Reports, https://github.com/Stabvalue/enhanced_downloader/issues
Project-URL: Source, https://github.com/Stabvalue/enhanced_downloader
Keywords: download multi-threading resume progress
Classifier: Development Status :: 4 - Beta
Classifier: Intended Audience :: Developers
Classifier: License :: OSI Approved :: MIT License
Classifier: Programming Language :: Python :: 3
Classifier: Programming Language :: Python :: 3.7
Classifier: Programming Language :: Python :: 3.8
Classifier: Programming Language :: Python :: 3.9
Classifier: Programming Language :: Python :: 3.10
Classifier: Programming Language :: Python :: 3.11
Classifier: Programming Language :: Python :: 3.12
Requires-Python: >=3.7
License-File: LICENSE
Requires-Dist: requests>=2.25.0
Requires-Dist: tqdm>=4.60.0
Requires-Dist: psutil>=5.0.0
Dynamic: author
Dynamic: author-email
Dynamic: classifier
Dynamic: description
Dynamic: description-content-type
Dynamic: home-page
Dynamic: keywords
Dynamic: license
Dynamic: license-file
Dynamic: project-url
Dynamic: requires-dist
Dynamic: requires-python
Dynamic: summary
